opencgi/__init__.cp310-win_amd64.pyd
opencgi/core.cp310-win_amd64.pyd
opencgi/main.cp310-win_amd64.pyd
opencgi-0.0.4.dist-info/METADATA
opencgi-0.0.4.dist-info/WHEEL
opencgi-0.0.4.dist-info/top_level.txt
opencgi-0.0.4.dist-info/RECORD
