Metadata-Version: 2.1
Name: opencgi
Version: 0.0.4
Summary: CGI Pipeline Tools
Author: initialfx
Author-email: initialfx@gmail.com
License: MIT
Requires-Python: >=3.10
Requires-Dist: gazu
Requires-Dist: pyreadline3
